{
	"$schema": "http://schema.management.azure.com/schemas/2015-01-01/deploymentTemplate.json#",
	"contentVersion": "1.0.0.0",
	"parameters": {
		"factoryName": {
			"type": "string",
			"metadata": "Data Factory name",
			"defaultValue": "pckADF"
		},
		"AzureBlobStorage1_connectionString": {
			"type": "secureString",
			"metadata": "Secure string for 'connectionString' of 'AzureBlobStorage1'"
		},
		"AzureDataLakeStorage1_accountKey": {
			"type": "secureString",
			"metadata": "Secure string for 'accountKey' of 'AzureDataLakeStorage1'"
		},
		"AzureSqlDatabase1_password": {
			"type": "secureString",
			"metadata": "Secure string for 'password' of 'AzureSqlDatabase1'"
		},
		"AzureSqlDatabase2_password": {
			"type": "secureString",
			"metadata": "Secure string for 'password' of 'AzureSqlDatabase2'"
		},
		"AzureSqlDatabase3_password": {
			"type": "secureString",
			"metadata": "Secure string for 'password' of 'AzureSqlDatabase3'"
		},
		"FileServer1_password": {
			"type": "secureString",
			"metadata": "Secure string for 'password' of 'FileServer1'"
		},
		"SqlServer1_password": {
			"type": "secureString",
			"metadata": "Secure string for 'password' of 'SqlServer1'"
		},
		"AzureDataLakeStorage1_properties_typeProperties_url": {
			"type": "string",
			"defaultValue": "https://pckstorageaccount.dfs.core.windows.net/"
		},
		"AzureSqlDatabase1_properties_typeProperties_server": {
			"type": "string",
			"defaultValue": "pcksqlserver.database.windows.net"
		},
		"AzureSqlDatabase1_properties_typeProperties_database": {
			"type": "string",
			"defaultValue": "cloudtraining"
		},
		"AzureSqlDatabase1_properties_typeProperties_userName": {
			"type": "string",
			"defaultValue": "pck"
		},
		"AzureSqlDatabase2_properties_typeProperties_server": {
			"type": "string",
			"defaultValue": "pcksqlserver.database.windows.net"
		},
		"AzureSqlDatabase2_properties_typeProperties_database": {
			"type": "string",
			"defaultValue": "DestinationDB"
		},
		"AzureSqlDatabase2_properties_typeProperties_userName": {
			"type": "string",
			"defaultValue": "pck"
		},
		"AzureSqlDatabase3_properties_typeProperties_server": {
			"type": "string",
			"defaultValue": "@{linkedService().serverName}"
		},
		"AzureSqlDatabase3_properties_typeProperties_database": {
			"type": "string",
			"defaultValue": "@{linkedService().databaseName}"
		},
		"AzureSqlDatabase3_properties_typeProperties_userName": {
			"type": "string",
			"defaultValue": "pck"
		},
		"FileServer1_properties_typeProperties_host": {
			"type": "string",
			"defaultValue": "//LAPTOP-5VQ2NFKL/SampleData"
		},
		"FileServer1_properties_typeProperties_userId": {
			"type": "string",
			"defaultValue": "//LAPTOP-5VQ2NFKL\\itspa"
		},
		"SqlServer1_properties_typeProperties_server": {
			"type": "string",
			"defaultValue": "LAPTOP-5VQ2NFKL"
		},
		"SqlServer1_properties_typeProperties_database": {
			"type": "string",
			"defaultValue": "cloudtraining"
		},
		"SqlServer1_properties_typeProperties_userName": {
			"type": "string",
			"defaultValue": "pck"
		}
	},
	"variables": {
		"factoryId": "[concat('Microsoft.DataFactory/factories/', parameters('factoryName'))]"
	},
	"resources": [
		{
			"name": "[concat(parameters('factoryName'), '/Copy_csv_Blob_to_SQL')]",
			"type": "Microsoft.DataFactory/factories/pipelines",
			"apiVersion": "2018-06-01",
			"properties": {
				"activities": [
					{
						"name": "Copy data1",
						"type": "Copy",
						"dependsOn": [],
						"policy": {
							"timeout": "0.12:00:00",
							"retry": 0,
							"retryIntervalInSeconds": 30,
							"secureOutput": false,
							"secureInput": false
						},
						"userProperties": [],
						"typeProperties": {
							"source": {
								"type": "DelimitedTextSource",
								"storeSettings": {
									"type": "AzureBlobStorageReadSettings",
									"recursive": true,
									"enablePartitionDiscovery": false
								},
								"formatSettings": {
									"type": "DelimitedTextReadSettings"
								}
							},
							"sink": {
								"type": "AzureSqlSink",
								"writeBehavior": "insert",
								"sqlWriterUseTableLock": false,
								"tableOption": "autoCreate",
								"disableMetricsCollection": false
							},
							"enableStaging": false,
							"translator": {
								"type": "TabularTranslator",
								"mappings": [
									{
										"source": {
											"name": "ID",
											"type": "String",
											"physicalType": "String"
										},
										"sink": {
											"name": "ID",
											"type": "String",
											"physicalType": "nvarchar"
										}
									},
									{
										"source": {
											"name": "Name",
											"type": "String",
											"physicalType": "String"
										},
										"sink": {
											"name": "Name",
											"type": "String",
											"physicalType": "nvarchar"
										}
									},
									{
										"source": {
											"name": "Age ",
											"type": "String",
											"physicalType": "String"
										},
										"sink": {
											"name": "Age ",
											"type": "String",
											"physicalType": "nvarchar"
										}
									}
								],
								"typeConversion": true,
								"typeConversionSettings": {
									"allowDataTruncation": true,
									"treatBooleanAsNumber": false
								}
							}
						},
						"inputs": [
							{
								"referenceName": "DelimitedText5",
								"type": "DatasetReference",
								"parameters": {}
							}
						],
						"outputs": [
							{
								"referenceName": "AzureSqlTable3",
								"type": "DatasetReference",
								"parameters": {}
							}
						]
					}
				],
				"policy": {
					"elapsedTimeMetric": {}
				},
				"annotations": []
			},
			"dependsOn": [
				"[concat(variables('factoryId'), '/datasets/DelimitedText5')]",
				"[concat(variables('factoryId'), '/datasets/AzureSqlTable3')]"
			]
		},
		{
			"name": "[concat(parameters('factoryName'), '/Data flow task2')]",
			"type": "Microsoft.DataFactory/factories/pipelines",
			"apiVersion": "2018-06-01",
			"properties": {
				"activities": [
					{
						"name": "Data flow1",
						"type": "ExecuteDataFlow",
						"dependsOn": [],
						"policy": {
							"timeout": "0.12:00:00",
							"retry": 0,
							"retryIntervalInSeconds": 30,
							"secureOutput": false,
							"secureInput": false
						},
						"userProperties": [],
						"typeProperties": {
							"dataflow": {
								"referenceName": "dataflow1",
								"type": "DataFlowReference",
								"parameters": {},
								"datasetParameters": {
									"Personaldetails": {},
									"locationdetails": {},
									"customerpurchases": {},
									"sink1": {
										"outputfile": "output"
									}
								}
							},
							"staging": {},
							"compute": {
								"coreCount": 8,
								"computeType": "General"
							},
							"traceLevel": "Fine"
						}
					}
				],
				"policy": {
					"elapsedTimeMetric": {}
				},
				"variables": {
					"switch": {
						"type": "String"
					}
				},
				"annotations": []
			},
			"dependsOn": [
				"[concat(variables('factoryId'), '/dataflows/dataflow1')]"
			]
		},
		{
			"name": "[concat(parameters('factoryName'), '/Incremental multiple files')]",
			"type": "Microsoft.DataFactory/factories/pipelines",
			"apiVersion": "2018-06-01",
			"properties": {
				"activities": [
					{
						"name": "forEach1",
						"type": "ForEach",
						"dependsOn": [],
						"userProperties": [],
						"typeProperties": {
							"items": {
								"value": "@pipeline().parameters.tableList",
								"type": "Expression"
							},
							"activities": [
								{
									"name": "LookupOldWaterMarkActivity",
									"type": "Lookup",
									"dependsOn": [],
									"policy": {
										"timeout": "0.12:00:00",
										"retry": 0,
										"retryIntervalInSeconds": 30,
										"secureOutput": false,
										"secureInput": false
									},
									"userProperties": [],
									"typeProperties": {
										"source": {
											"type": "AzureSqlSource",
											"sqlReaderQuery": {
												"value": "select * from watermarktable where TableName  =  '@{item().TABLE_NAME}'",
												"type": "Expression"
											},
											"queryTimeout": "02:00:00",
											"partitionOption": "None"
										},
										"dataset": {
											"referenceName": "AzureSqlTable1",
											"type": "DatasetReference",
											"parameters": {}
										}
									}
								},
								{
									"name": "LookupNewWaterMarkActivity",
									"type": "Lookup",
									"dependsOn": [],
									"policy": {
										"timeout": "0.12:00:00",
										"retry": 0,
										"retryIntervalInSeconds": 30,
										"secureOutput": false,
										"secureInput": false
									},
									"userProperties": [],
									"typeProperties": {
										"source": {
											"type": "AzureSqlSource",
											"sqlReaderQuery": {
												"value": "select MAX(@{item().WaterMark_Column}) as NewWatermarkvalue from @{item().TABLE_NAME}",
												"type": "Expression"
											},
											"queryTimeout": "02:00:00",
											"partitionOption": "None"
										},
										"dataset": {
											"referenceName": "sourcetables",
											"type": "DatasetReference",
											"parameters": {}
										}
									}
								},
								{
									"name": "IncrementalCopyActivity",
									"type": "Copy",
									"dependsOn": [
										{
											"activity": "LookupOldWaterMarkActivity",
											"dependencyConditions": [
												"Succeeded"
											]
										},
										{
											"activity": "LookupNewWaterMarkActivity",
											"dependencyConditions": [
												"Succeeded"
											]
										}
									],
									"policy": {
										"timeout": "0.12:00:00",
										"retry": 0,
										"retryIntervalInSeconds": 30,
										"secureOutput": false,
										"secureInput": false
									},
									"userProperties": [],
									"typeProperties": {
										"source": {
											"type": "AzureSqlSource",
											"sqlReaderQuery": {
												"value": "select * from @{item().TABLE_NAME} where @{item().WaterMark_Column} > '@{activity('LookupOldWaterMarkActivity').output.firstRow.WatermarkValue}' and @{item().WaterMark_Column} <= '@{activity('LookupNewWaterMarkActivity').output.firstRow.NewWatermarkvalue}'",
												"type": "Expression"
											},
											"queryTimeout": "02:00:00",
											"partitionOption": "None"
										},
										"sink": {
											"type": "DelimitedTextSink",
											"storeSettings": {
												"type": "AzureBlobStorageWriteSettings"
											},
											"formatSettings": {
												"type": "DelimitedTextWriteSettings",
												"quoteAllText": true,
												"fileExtension": ".txt"
											}
										},
										"enableStaging": false,
										"translator": {
											"type": "TabularTranslator",
											"typeConversion": true,
											"typeConversionSettings": {
												"allowDataTruncation": true,
												"treatBooleanAsNumber": false
											}
										}
									},
									"inputs": [
										{
											"referenceName": "sourcetables",
											"type": "DatasetReference",
											"parameters": {}
										}
									],
									"outputs": [
										{
											"referenceName": "DelimitedText2",
											"type": "DatasetReference",
											"parameters": {}
										}
									]
								},
								{
									"name": "StoredProceduretoWriteWatermarkActivity",
									"type": "SqlServerStoredProcedure",
									"dependsOn": [
										{
											"activity": "IncrementalCopyActivity",
											"dependencyConditions": [
												"Succeeded"
											]
										}
									],
									"policy": {
										"timeout": "0.12:00:00",
										"retry": 0,
										"retryIntervalInSeconds": 30,
										"secureOutput": false,
										"secureInput": false
									},
									"userProperties": [],
									"typeProperties": {
										"storedProcedureName": "[[dbo].[usp_write_watermark]",
										"storedProcedureParameters": {
											"LastModifiedtime": {
												"value": {
													"value": "@{activity('LookupNewWaterMarkActivity').output.firstRow.NewWatermarkvalue}\n",
													"type": "Expression"
												},
												"type": "Datetime"
											},
											"TableName": {
												"value": {
													"value": "@{activity('LookupOldWaterMarkActivity').output.firstRow.TableName}\n",
													"type": "Expression"
												},
												"type": "String"
											}
										}
									},
									"linkedServiceName": {
										"referenceName": "AzureSqlDatabase1",
										"type": "LinkedServiceReference"
									}
								}
							]
						}
					}
				],
				"policy": {
					"elapsedTimeMetric": {}
				},
				"parameters": {
					"tableList": {
						"type": "array"
					}
				},
				"annotations": []
			},
			"dependsOn": [
				"[concat(variables('factoryId'), '/datasets/AzureSqlTable1')]",
				"[concat(variables('factoryId'), '/datasets/sourcetables')]",
				"[concat(variables('factoryId'), '/datasets/DelimitedText2')]",
				"[concat(variables('factoryId'), '/linkedServices/AzureSqlDatabase1')]"
			]
		},
		{
			"name": "[concat(parameters('factoryName'), '/Incremental single file')]",
			"type": "Microsoft.DataFactory/factories/pipelines",
			"apiVersion": "2018-06-01",
			"properties": {
				"activities": [
					{
						"name": "LookupOldWaterMarkActivity",
						"type": "Lookup",
						"dependsOn": [],
						"policy": {
							"timeout": "0.12:00:00",
							"retry": 0,
							"retryIntervalInSeconds": 30,
							"secureOutput": false,
							"secureInput": false
						},
						"userProperties": [],
						"typeProperties": {
							"source": {
								"type": "AzureSqlSource",
								"queryTimeout": "02:00:00",
								"partitionOption": "None"
							},
							"dataset": {
								"referenceName": "AzureSqlTable1",
								"type": "DatasetReference",
								"parameters": {}
							}
						}
					},
					{
						"name": "LookupNewWaterMarkActivity",
						"type": "Lookup",
						"dependsOn": [],
						"policy": {
							"timeout": "0.12:00:00",
							"retry": 0,
							"retryIntervalInSeconds": 30,
							"secureOutput": false,
							"secureInput": false
						},
						"userProperties": [],
						"typeProperties": {
							"source": {
								"type": "AzureSqlSource",
								"sqlReaderQuery": "select MAX(LastModifytime) as NewWatermarkvalue from data_source_table",
								"queryTimeout": "02:00:00",
								"partitionOption": "None"
							},
							"dataset": {
								"referenceName": "AzureSqlTable2",
								"type": "DatasetReference",
								"parameters": {}
							}
						}
					},
					{
						"name": "IncrementalCopyActivity",
						"type": "Copy",
						"dependsOn": [
							{
								"activity": "LookupOldWaterMarkActivity",
								"dependencyConditions": [
									"Succeeded"
								]
							},
							{
								"activity": "LookupNewWaterMarkActivity",
								"dependencyConditions": [
									"Succeeded"
								]
							}
						],
						"policy": {
							"timeout": "0.12:00:00",
							"retry": 0,
							"retryIntervalInSeconds": 30,
							"secureOutput": false,
							"secureInput": false
						},
						"userProperties": [],
						"typeProperties": {
							"source": {
								"type": "AzureSqlSource",
								"sqlReaderQuery": {
									"value": "select * from data_source_table where LastModifytime > '@{activity('LookupOldWaterMarkActivity').output.firstRow.WatermarkValue}' and LastModifytime <= '@{activity('LookupNewWaterMarkActivity').output.firstRow.NewWatermarkvalue}'",
									"type": "Expression"
								},
								"queryTimeout": "02:00:00",
								"partitionOption": "None"
							},
							"sink": {
								"type": "DelimitedTextSink",
								"storeSettings": {
									"type": "AzureBlobStorageWriteSettings"
								},
								"formatSettings": {
									"type": "DelimitedTextWriteSettings",
									"quoteAllText": true,
									"fileExtension": ".txt"
								}
							},
							"enableStaging": false,
							"translator": {
								"type": "TabularTranslator",
								"typeConversion": true,
								"typeConversionSettings": {
									"allowDataTruncation": true,
									"treatBooleanAsNumber": false
								}
							}
						},
						"inputs": [
							{
								"referenceName": "AzureSqlTable2",
								"type": "DatasetReference",
								"parameters": {}
							}
						],
						"outputs": [
							{
								"referenceName": "DelimitedText1",
								"type": "DatasetReference",
								"parameters": {}
							}
						]
					},
					{
						"name": "StoredProceduretoWriteWatermarkActivity",
						"type": "SqlServerStoredProcedure",
						"dependsOn": [
							{
								"activity": "IncrementalCopyActivity",
								"dependencyConditions": [
									"Succeeded"
								]
							}
						],
						"policy": {
							"timeout": "0.12:00:00",
							"retry": 0,
							"retryIntervalInSeconds": 30,
							"secureOutput": false,
							"secureInput": false
						},
						"userProperties": [],
						"typeProperties": {
							"storedProcedureName": "[[dbo].[usp_write_watermark]",
							"storedProcedureParameters": {
								"LastModifiedtime": {
									"value": {
										"value": "@{activity('LookupNewWaterMarkActivity').output.firstRow.NewWatermarkvalue}",
										"type": "Expression"
									},
									"type": "Datetime"
								},
								"TableName": {
									"value": {
										"value": "@{activity('LookupOldWaterMarkActivity').output.firstRow.TableName}",
										"type": "Expression"
									},
									"type": "String"
								}
							}
						},
						"linkedServiceName": {
							"referenceName": "AzureSqlDatabase1",
							"type": "LinkedServiceReference"
						}
					}
				],
				"policy": {
					"elapsedTimeMetric": {}
				},
				"annotations": []
			},
			"dependsOn": [
				"[concat(variables('factoryId'), '/datasets/AzureSqlTable1')]",
				"[concat(variables('factoryId'), '/datasets/AzureSqlTable2')]",
				"[concat(variables('factoryId'), '/datasets/DelimitedText1')]",
				"[concat(variables('factoryId'), '/linkedServices/AzureSqlDatabase1')]"
			]
		},
		{
			"name": "[concat(parameters('factoryName'), '/Mapping data flow usecase')]",
			"type": "Microsoft.DataFactory/factories/pipelines",
			"apiVersion": "2018-06-01",
			"properties": {
				"activities": [
					{
						"name": "Data flow1",
						"type": "ExecuteDataFlow",
						"dependsOn": [],
						"policy": {
							"timeout": "0.12:00:00",
							"retry": 0,
							"retryIntervalInSeconds": 30,
							"secureOutput": false,
							"secureInput": false
						},
						"userProperties": [],
						"typeProperties": {
							"dataflow": {
								"referenceName": "dataflow2",
								"type": "DataFlowReference",
								"parameters": {},
								"datasetParameters": {
									"source1": {},
									"source2": {},
									"sink1": {},
									"sink2": {}
								}
							},
							"staging": {},
							"compute": {
								"coreCount": 8,
								"computeType": "General"
							},
							"traceLevel": "Fine"
						}
					}
				],
				"policy": {
					"elapsedTimeMetric": {}
				},
				"annotations": []
			},
			"dependsOn": [
				"[concat(variables('factoryId'), '/dataflows/dataflow2')]"
			]
		},
		{
			"name": "[concat(parameters('factoryName'), '/Parameters')]",
			"type": "Microsoft.DataFactory/factories/pipelines",
			"apiVersion": "2018-06-01",
			"properties": {
				"activities": [
					{
						"name": "Lookup1",
						"type": "Lookup",
						"dependsOn": [],
						"policy": {
							"timeout": "0.12:00:00",
							"retry": 0,
							"retryIntervalInSeconds": 30,
							"secureOutput": false,
							"secureInput": false
						},
						"userProperties": [],
						"typeProperties": {
							"source": {
								"type": "JsonSource",
								"storeSettings": {
									"type": "AzureBlobFSReadSettings",
									"recursive": true,
									"enablePartitionDiscovery": false
								},
								"formatSettings": {
									"type": "JsonReadSettings"
								}
							},
							"dataset": {
								"referenceName": "Json1",
								"type": "DatasetReference",
								"parameters": {}
							}
						}
					},
					{
						"name": "Set variable1",
						"type": "SetVariable",
						"dependsOn": [
							{
								"activity": "Lookup1",
								"dependencyConditions": [
									"Succeeded"
								]
							}
						],
						"policy": {
							"secureOutput": false,
							"secureInput": false
						},
						"userProperties": [],
						"typeProperties": {
							"variableName": "sql_server",
							"value": {
								"value": "@activity('Lookup1').output.firstRow.destination.serverName",
								"type": "Expression"
							}
						}
					},
					{
						"name": "Set variable2",
						"type": "SetVariable",
						"dependsOn": [
							{
								"activity": "Lookup1",
								"dependencyConditions": [
									"Succeeded"
								]
							}
						],
						"policy": {
							"secureOutput": false,
							"secureInput": false
						},
						"userProperties": [],
						"typeProperties": {
							"variableName": "database",
							"value": {
								"value": "@activity('Lookup1').output.firstRow.destination.databaseName",
								"type": "Expression"
							}
						}
					},
					{
						"name": "Set variable3",
						"type": "SetVariable",
						"dependsOn": [
							{
								"activity": "Lookup1",
								"dependencyConditions": [
									"Succeeded"
								]
							}
						],
						"policy": {
							"secureOutput": false,
							"secureInput": false
						},
						"userProperties": [],
						"typeProperties": {
							"variableName": "tablename",
							"value": {
								"value": "@activity('Lookup1').output.firstRow.destination.tableName",
								"type": "Expression"
							}
						}
					},
					{
						"name": "Set variable4",
						"type": "SetVariable",
						"dependsOn": [
							{
								"activity": "Lookup1",
								"dependencyConditions": [
									"Succeeded"
								]
							}
						],
						"policy": {
							"secureOutput": false,
							"secureInput": false
						},
						"userProperties": [],
						"typeProperties": {
							"variableName": "adlspath",
							"value": {
								"value": "@activity('Lookup1').output.firstRow.source.adlsPath",
								"type": "Expression"
							}
						}
					},
					{
						"name": "Set variable5",
						"type": "SetVariable",
						"dependsOn": [
							{
								"activity": "Lookup1",
								"dependencyConditions": [
									"Succeeded"
								]
							}
						],
						"policy": {
							"secureOutput": false,
							"secureInput": false
						},
						"userProperties": [],
						"typeProperties": {
							"variableName": "filename",
							"value": {
								"value": "@activity('Lookup1').output.firstRow.source.fileName",
								"type": "Expression"
							}
						}
					},
					{
						"name": "Data flow1",
						"type": "ExecuteDataFlow",
						"dependsOn": [
							{
								"activity": "Set variable1",
								"dependencyConditions": [
									"Succeeded"
								]
							},
							{
								"activity": "Set variable2",
								"dependencyConditions": [
									"Succeeded"
								]
							},
							{
								"activity": "Set variable3",
								"dependencyConditions": [
									"Succeeded"
								]
							},
							{
								"activity": "Set variable4",
								"dependencyConditions": [
									"Succeeded"
								]
							},
							{
								"activity": "Set variable5",
								"dependencyConditions": [
									"Succeeded"
								]
							}
						],
						"policy": {
							"timeout": "0.12:00:00",
							"retry": 0,
							"retryIntervalInSeconds": 30,
							"secureOutput": false,
							"secureInput": false
						},
						"userProperties": [],
						"typeProperties": {
							"dataflow": {
								"referenceName": "dataflow3",
								"type": "DataFlowReference",
								"parameters": {
									"adlsPath": {
										"value": "'@{variables('adlspath')}'",
										"type": "Expression"
									},
									"fileName": {
										"value": "'@{variables('filename')}'",
										"type": "Expression"
									}
								},
								"datasetParameters": {
									"source1": {},
									"sink1": {
										"tableName": {
											"value": "@variables('tablename')",
											"type": "Expression"
										},
										"databaseName": {
											"value": "@variables('database')",
											"type": "Expression"
										},
										"servername": {
											"value": "@variables('sql_server')",
											"type": "Expression"
										}
									}
								}
							},
							"staging": {},
							"compute": {
								"coreCount": 8,
								"computeType": "General"
							},
							"traceLevel": "Fine"
						}
					}
				],
				"policy": {
					"elapsedTimeMetric": {}
				},
				"variables": {
					"sql_server": {
						"type": "String"
					},
					"database": {
						"type": "String"
					},
					"tablename": {
						"type": "String"
					},
					"adlspath": {
						"type": "String"
					},
					"filename": {
						"type": "String"
					}
				},
				"annotations": []
			},
			"dependsOn": [
				"[concat(variables('factoryId'), '/datasets/Json1')]",
				"[concat(variables('factoryId'), '/dataflows/dataflow3')]"
			]
		},
		{
			"name": "[concat(parameters('factoryName'), '/control flow child')]",
			"type": "Microsoft.DataFactory/factories/pipelines",
			"apiVersion": "2018-06-01",
			"properties": {
				"activities": [
					{
						"name": "Copy data1",
						"type": "Copy",
						"dependsOn": [],
						"policy": {
							"timeout": "0.12:00:00",
							"retry": 0,
							"retryIntervalInSeconds": 30,
							"secureOutput": false,
							"secureInput": false
						},
						"userProperties": [],
						"typeProperties": {
							"source": {
								"type": "DelimitedTextSource",
								"additionalColumns": [
									{
										"name": "filename",
										"value": {
											"value": "@pipeline().parameters.filename",
											"type": "Expression"
										}
									},
									{
										"name": "time",
										"value": {
											"value": "@pipeline().TriggerTime",
											"type": "Expression"
										}
									}
								],
								"storeSettings": {
									"type": "AzureBlobFSReadSettings",
									"recursive": true,
									"enablePartitionDiscovery": false
								},
								"formatSettings": {
									"type": "DelimitedTextReadSettings"
								}
							},
							"sink": {
								"type": "AzureSqlSink",
								"writeBehavior": "insert",
								"sqlWriterUseTableLock": false
							},
							"enableStaging": false,
							"translator": {
								"type": "TabularTranslator",
								"mappings": [
									{
										"source": {
											"name": "ID",
											"type": "String"
										},
										"sink": {
											"name": "ID",
											"type": "int",
											"physicalType": "int",
											"precision": 10
										}
									},
									{
										"source": {
											"name": "Name",
											"type": "String"
										},
										"sink": {
											"name": "Name",
											"type": "nvarchar",
											"physicalType": "nvarchar"
										}
									},
									{
										"source": {
											"name": "Age ",
											"type": "String"
										},
										"sink": {
											"name": "Age",
											"type": "int",
											"physicalType": "int",
											"precision": 10
										}
									}
								],
								"typeConversion": true,
								"typeConversionSettings": {
									"allowDataTruncation": true,
									"treatBooleanAsNumber": false
								}
							}
						},
						"inputs": [
							{
								"referenceName": "DelimitedText4",
								"type": "DatasetReference",
								"parameters": {
									"filename": {
										"value": "@pipeline().parameters.filename",
										"type": "Expression"
									}
								}
							}
						],
						"outputs": [
							{
								"referenceName": "processeddatatable",
								"type": "DatasetReference",
								"parameters": {}
							}
						]
					},
					{
						"name": "Wait1",
						"type": "Wait",
						"dependsOn": [
							{
								"activity": "Copy data1",
								"dependencyConditions": [
									"Succeeded"
								]
							}
						],
						"userProperties": [],
						"typeProperties": {
							"waitTimeInSeconds": 10
						}
					}
				],
				"policy": {
					"elapsedTimeMetric": {}
				},
				"parameters": {
					"filename": {
						"type": "string"
					}
				},
				"variables": {
					"switch": {
						"type": "String"
					}
				},
				"annotations": []
			},
			"dependsOn": [
				"[concat(variables('factoryId'), '/datasets/DelimitedText4')]",
				"[concat(variables('factoryId'), '/datasets/processeddatatable')]"
			]
		},
		{
			"name": "[concat(parameters('factoryName'), '/control flow master')]",
			"type": "Microsoft.DataFactory/factories/pipelines",
			"apiVersion": "2018-06-01",
			"properties": {
				"activities": [
					{
						"name": "Get Metadata1",
						"type": "GetMetadata",
						"dependsOn": [],
						"policy": {
							"timeout": "0.12:00:00",
							"retry": 0,
							"retryIntervalInSeconds": 30,
							"secureOutput": false,
							"secureInput": false
						},
						"userProperties": [],
						"typeProperties": {
							"dataset": {
								"referenceName": "DelimitedText3",
								"type": "DatasetReference",
								"parameters": {}
							},
							"fieldList": [
								"childItems"
							],
							"storeSettings": {
								"type": "AzureBlobStorageReadSettings",
								"recursive": true,
								"enablePartitionDiscovery": false
							},
							"formatSettings": {
								"type": "DelimitedTextReadSettings"
							}
						}
					},
					{
						"name": "Filter1",
						"type": "Filter",
						"dependsOn": [
							{
								"activity": "Get Metadata1",
								"dependencyConditions": [
									"Succeeded"
								]
							}
						],
						"userProperties": [],
						"typeProperties": {
							"items": {
								"value": "@activity('Get Metadata1').output.childItems",
								"type": "Expression"
							},
							"condition": {
								"value": "@endswith(item().name,'.csv')",
								"type": "Expression"
							}
						}
					},
					{
						"name": "ForEach1",
						"type": "ForEach",
						"dependsOn": [
							{
								"activity": "Filter1",
								"dependencyConditions": [
									"Succeeded"
								]
							}
						],
						"userProperties": [],
						"typeProperties": {
							"items": {
								"value": "@activity('Filter1').output.value",
								"type": "Expression"
							},
							"batchCount": 1,
							"activities": [
								{
									"name": "Set variable1",
									"type": "SetVariable",
									"dependsOn": [],
									"policy": {
										"secureOutput": false,
										"secureInput": false
									},
									"userProperties": [],
									"typeProperties": {
										"variableName": "currentfile",
										"value": {
											"value": "@item().name",
											"type": "Expression"
										}
									}
								},
								{
									"name": "Switch1",
									"type": "Switch",
									"dependsOn": [
										{
											"activity": "Set variable2",
											"dependencyConditions": [
												"Succeeded"
											]
										}
									],
									"userProperties": [],
									"typeProperties": {
										"on": {
											"value": "@variables('switch')",
											"type": "Expression"
										},
										"cases": [
											{
												"value": "a",
												"activities": [
													{
														"name": "Execute Pipeline1",
														"type": "ExecutePipeline",
														"dependsOn": [],
														"policy": {
															"secureInput": false
														},
														"userProperties": [],
														"typeProperties": {
															"pipeline": {
																"referenceName": "control flow child",
																"type": "PipelineReference"
															},
															"waitOnCompletion": true,
															"parameters": {
																"filename": {
																	"value": "@variables('currentfile')",
																	"type": "Expression"
																}
															}
														}
													}
												]
											},
											{
												"value": "b",
												"activities": [
													{
														"name": "Execute Pipeline2",
														"type": "ExecutePipeline",
														"dependsOn": [],
														"policy": {
															"secureInput": false
														},
														"userProperties": [],
														"typeProperties": {
															"pipeline": {
																"referenceName": "control flow child",
																"type": "PipelineReference"
															},
															"waitOnCompletion": true,
															"parameters": {
																"filename": {
																	"value": "@variables('currentfile')",
																	"type": "Expression"
																}
															}
														}
													}
												]
											},
											{
												"value": "c",
												"activities": [
													{
														"name": "Execute Pipeline3",
														"type": "ExecutePipeline",
														"dependsOn": [],
														"policy": {
															"secureInput": false
														},
														"userProperties": [],
														"typeProperties": {
															"pipeline": {
																"referenceName": "control flow child",
																"type": "PipelineReference"
															},
															"waitOnCompletion": true,
															"parameters": {
																"filename": {
																	"value": "@variables('currentfile')",
																	"type": "Expression"
																}
															}
														}
													}
												]
											}
										]
									}
								},
								{
									"name": "Get Metadata2",
									"type": "GetMetadata",
									"dependsOn": [
										{
											"activity": "Set variable1",
											"dependencyConditions": [
												"Succeeded"
											]
										}
									],
									"policy": {
										"timeout": "0.12:00:00",
										"retry": 0,
										"retryIntervalInSeconds": 30,
										"secureOutput": false,
										"secureInput": false
									},
									"userProperties": [],
									"typeProperties": {
										"dataset": {
											"referenceName": "DelimitedText4",
											"type": "DatasetReference",
											"parameters": {
												"filename": {
													"value": "@item().name",
													"type": "Expression"
												}
											}
										},
										"fieldList": [
											"size"
										],
										"storeSettings": {
											"type": "AzureBlobFSReadSettings",
											"recursive": true,
											"enablePartitionDiscovery": false
										},
										"formatSettings": {
											"type": "DelimitedTextReadSettings"
										}
									}
								},
								{
									"name": "Set variable2",
									"type": "SetVariable",
									"dependsOn": [
										{
											"activity": "Get Metadata2",
											"dependencyConditions": [
												"Succeeded"
											]
										}
									],
									"policy": {
										"secureOutput": false,
										"secureInput": false
									},
									"userProperties": [],
									"typeProperties": {
										"variableName": "switch",
										"value": {
											"value": "@{\n    replace(trim(if(greaterOrEquals(activity('Get Metadata2').output.size,5242880), 'c',\n    if(\n        lessOrEquals(activity('Get Metadata2').output.size,1048576), 'a', 'b'\n    )\n    )), '\\n', '')\n}",
											"type": "Expression"
										}
									}
								}
							]
						}
					}
				],
				"policy": {
					"elapsedTimeMetric": {}
				},
				"variables": {
					"currentfile": {
						"type": "String"
					},
					"switch": {
						"type": "String"
					}
				},
				"annotations": []
			},
			"dependsOn": [
				"[concat(variables('factoryId'), '/datasets/DelimitedText3')]",
				"[concat(variables('factoryId'), '/datasets/DelimitedText4')]",
				"[concat(variables('factoryId'), '/pipelines/control flow child')]"
			]
		},
		{
			"name": "[concat(parameters('factoryName'), '/incremental file')]",
			"type": "Microsoft.DataFactory/factories/pipelines",
			"apiVersion": "2018-06-01",
			"properties": {
				"activities": [
					{
						"name": "Lookup1",
						"type": "Lookup",
						"dependsOn": [],
						"policy": {
							"timeout": "0.12:00:00",
							"retry": 0,
							"retryIntervalInSeconds": 30,
							"secureOutput": false,
							"secureInput": false
						},
						"userProperties": [],
						"typeProperties": {
							"source": {
								"type": "AzureSqlSource",
								"queryTimeout": "02:00:00",
								"partitionOption": "None"
							},
							"dataset": {
								"referenceName": "configtable",
								"type": "DatasetReference",
								"parameters": {}
							},
							"firstRowOnly": false
						}
					},
					{
						"name": "Filter1",
						"type": "Filter",
						"dependsOn": [
							{
								"activity": "Lookup1",
								"dependencyConditions": [
									"Succeeded"
								]
							}
						],
						"userProperties": [],
						"typeProperties": {
							"items": {
								"value": "@activity('Lookup1').output.value\n",
								"type": "Expression"
							},
							"condition": {
								"value": "@equals(item().Enabled, 1)",
								"type": "Expression"
							}
						}
					},
					{
						"name": "ForEach1",
						"type": "ForEach",
						"dependsOn": [
							{
								"activity": "Filter1",
								"dependencyConditions": [
									"Succeeded"
								]
							}
						],
						"userProperties": [],
						"typeProperties": {
							"items": {
								"value": "@activity('Filter1').output",
								"type": "Expression"
							},
							"activities": [
								{
									"name": "Copy data1",
									"type": "Copy",
									"dependsOn": [],
									"policy": {
										"timeout": "0.12:00:00",
										"retry": 0,
										"retryIntervalInSeconds": 30,
										"secureOutput": false,
										"secureInput": false
									},
									"userProperties": [],
									"typeProperties": {
										"source": {
											"type": "AzureSqlSource",
											"queryTimeout": "02:00:00",
											"partitionOption": "None"
										},
										"sink": {
											"type": "AzureSqlSink",
											"writeBehavior": "insert",
											"sqlWriterUseTableLock": false,
											"tableOption": "autoCreate",
											"disableMetricsCollection": false
										},
										"enableStaging": false,
										"translator": {
											"type": "TabularTranslator",
											"typeConversion": true,
											"typeConversionSettings": {
												"allowDataTruncation": true,
												"treatBooleanAsNumber": false
											}
										}
									},
									"inputs": [
										{
											"referenceName": "AzureSqlSourceTable",
											"type": "DatasetReference",
											"parameters": {
												"tablename": {
													"value": "@item().Name",
													"type": "Expression"
												}
											}
										}
									],
									"outputs": [
										{
											"referenceName": "DestinationDB",
											"type": "DatasetReference",
											"parameters": {
												"tablename": {
													"value": "@item().Name",
													"type": "Expression"
												}
											}
										}
									]
								}
							]
						}
					}
				],
				"policy": {
					"elapsedTimeMetric": {}
				},
				"annotations": []
			},
			"dependsOn": [
				"[concat(variables('factoryId'), '/datasets/configtable')]",
				"[concat(variables('factoryId'), '/datasets/AzureSqlSourceTable')]",
				"[concat(variables('factoryId'), '/datasets/DestinationDB')]"
			]
		},
		{
			"name": "[concat(parameters('factoryName'), '/pipeline3')]",
			"type": "Microsoft.DataFactory/factories/pipelines",
			"apiVersion": "2018-06-01",
			"properties": {
				"activities": [
					{
						"name": "IterateSQLTables",
						"type": "ForEach",
						"dependsOn": [],
						"userProperties": [],
						"typeProperties": {
							"items": {
								"value": "@pipeline().parameters.tableList",
								"type": "Expression"
							},
							"activities": [
								{
									"name": "LookupOldWaterMarkActivity",
									"type": "Lookup",
									"dependsOn": [],
									"policy": {
										"timeout": "0.12:00:00",
										"retry": 0,
										"retryIntervalInSeconds": 30,
										"secureOutput": false,
										"secureInput": false
									},
									"userProperties": [],
									"typeProperties": {
										"source": {
											"type": "AzureSqlSource",
											"sqlReaderQuery": {
												"value": "select * from watermarktable where TableName  =  '@{item().TABLE_NAME}'",
												"type": "Expression"
											},
											"queryTimeout": "02:00:00",
											"partitionOption": "None"
										},
										"dataset": {
											"referenceName": "AzureSqlTable1",
											"type": "DatasetReference",
											"parameters": {}
										}
									}
								},
								{
									"name": "LookupNewWaterMarkActivity",
									"type": "Lookup",
									"dependsOn": [],
									"policy": {
										"timeout": "0.12:00:00",
										"retry": 0,
										"retryIntervalInSeconds": 30,
										"secureOutput": false,
										"secureInput": false
									},
									"userProperties": [],
									"typeProperties": {
										"source": {
											"type": "SqlServerSource",
											"sqlReaderQuery": {
												"value": "select MAX(@{item().WaterMark_Column}) as NewWatermarkvalue from @{item().TABLE_NAME}",
												"type": "Expression"
											},
											"queryTimeout": "02:00:00",
											"partitionOption": "None"
										},
										"dataset": {
											"referenceName": "SourceTables2",
											"type": "DatasetReference",
											"parameters": {}
										}
									}
								},
								{
									"name": "IncrementalCopyActivity",
									"type": "Copy",
									"dependsOn": [
										{
											"activity": "LookupOldWaterMarkActivity",
											"dependencyConditions": [
												"Succeeded"
											]
										},
										{
											"activity": "LookupNewWaterMarkActivity",
											"dependencyConditions": [
												"Succeeded"
											]
										}
									],
									"policy": {
										"timeout": "0.12:00:00",
										"retry": 0,
										"retryIntervalInSeconds": 30,
										"secureOutput": false,
										"secureInput": false
									},
									"userProperties": [],
									"typeProperties": {
										"source": {
											"type": "SqlServerSource",
											"sqlReaderQuery": {
												"value": "select * from @{item().TABLE_NAME} where @{item().WaterMark_Column} > '@{activity('LookupOldWaterMarkActivity').output.firstRow.WatermarkValue}' and @{item().WaterMark_Column} <= '@{activity('LookupNewWaterMarkActivity').output.firstRow.NewWatermarkvalue}'",
												"type": "Expression"
											},
											"queryTimeout": "02:00:00",
											"partitionOption": "None"
										},
										"sink": {
											"type": "AzureSqlSink",
											"sqlWriterStoredProcedureName": {
												"value": "@{item().StoredProcedureNameForMergeOperation}",
												"type": "Expression"
											},
											"sqlWriterTableType": {
												"value": "@{item().TableType}",
												"type": "Expression"
											},
											"storedProcedureTableTypeParameterName": {
												"value": "@{item().TABLE_NAME}",
												"type": "Expression"
											},
											"disableMetricsCollection": false
										},
										"enableStaging": false,
										"translator": {
											"type": "TabularTranslator",
											"typeConversion": true,
											"typeConversionSettings": {
												"allowDataTruncation": true,
												"treatBooleanAsNumber": false
											}
										}
									},
									"inputs": [
										{
											"referenceName": "SourceTables2",
											"type": "DatasetReference",
											"parameters": {}
										}
									],
									"outputs": [
										{
											"referenceName": "SinkDataset",
											"type": "DatasetReference",
											"parameters": {
												"SinkTableName": "@{item().TABLE_NAME}"
											}
										}
									]
								},
								{
									"name": "StoredProceduretoWriteWatermarkActivity",
									"type": "SqlServerStoredProcedure",
									"dependsOn": [
										{
											"activity": "IncrementalCopyActivity",
											"dependencyConditions": [
												"Succeeded"
											]
										}
									],
									"policy": {
										"timeout": "0.12:00:00",
										"retry": 0,
										"retryIntervalInSeconds": 30,
										"secureOutput": false,
										"secureInput": false
									},
									"userProperties": [],
									"typeProperties": {
										"storedProcedureName": "[[dbo].[usp_write_watermark]",
										"storedProcedureParameters": {
											"LastModifiedtime": {
												"value": {
													"value": "@{activity('LookupNewWaterMarkActivity').output.firstRow.NewWatermarkvalue}",
													"type": "Expression"
												},
												"type": "Datetime"
											},
											"TableName": {
												"value": {
													"value": "@{activity('LookupOldWaterMarkActivity').output.firstRow.TableName}",
													"type": "Expression"
												},
												"type": "String"
											}
										}
									},
									"linkedServiceName": {
										"referenceName": "AzureSqlDatabase1",
										"type": "LinkedServiceReference"
									}
								}
							]
						}
					}
				],
				"policy": {
					"elapsedTimeMetric": {}
				},
				"parameters": {
					"tableList": {
						"type": "array"
					}
				},
				"annotations": []
			},
			"dependsOn": [
				"[concat(variables('factoryId'), '/datasets/AzureSqlTable1')]",
				"[concat(variables('factoryId'), '/datasets/SourceTables2')]",
				"[concat(variables('factoryId'), '/datasets/SinkDataset')]",
				"[concat(variables('factoryId'), '/linkedServices/AzureSqlDatabase1')]"
			]
		},
		{
			"name": "[concat(parameters('factoryName'), '/AzureSqlSourceTable')]",
			"type": "Microsoft.DataFactory/factories/datasets",
			"apiVersion": "2018-06-01",
			"properties": {
				"linkedServiceName": {
					"referenceName": "AzureSqlDatabase1",
					"type": "LinkedServiceReference"
				},
				"parameters": {
					"tablename": {
						"type": "String"
					}
				},
				"annotations": [],
				"type": "AzureSqlTable",
				"schema": [],
				"typeProperties": {
					"table": {
						"value": "@dataset().tablename",
						"type": "Expression"
					}
				}
			},
			"dependsOn": [
				"[concat(variables('factoryId'), '/linkedServices/AzureSqlDatabase1')]"
			]
		},
		{
			"name": "[concat(parameters('factoryName'), '/AzureSqlTable1')]",
			"type": "Microsoft.DataFactory/factories/datasets",
			"apiVersion": "2018-06-01",
			"properties": {
				"linkedServiceName": {
					"referenceName": "AzureSqlDatabase1",
					"type": "LinkedServiceReference"
				},
				"annotations": [],
				"type": "AzureSqlTable",
				"schema": [
					{
						"name": "TableName",
						"type": "varchar"
					},
					{
						"name": "WatermarkValue",
						"type": "datetime",
						"precision": 23,
						"scale": 3
					}
				],
				"typeProperties": {
					"schema": "dbo",
					"table": "watermarktable"
				}
			},
			"dependsOn": [
				"[concat(variables('factoryId'), '/linkedServices/AzureSqlDatabase1')]"
			]
		},
		{
			"name": "[concat(parameters('factoryName'), '/AzureSqlTable2')]",
			"type": "Microsoft.DataFactory/factories/datasets",
			"apiVersion": "2018-06-01",
			"properties": {
				"linkedServiceName": {
					"referenceName": "AzureSqlDatabase1",
					"type": "LinkedServiceReference"
				},
				"annotations": [],
				"type": "AzureSqlTable",
				"schema": [
					{
						"name": "PersonID",
						"type": "int",
						"precision": 10
					},
					{
						"name": "Name",
						"type": "varchar"
					},
					{
						"name": "LastModifytime",
						"type": "datetime",
						"precision": 23,
						"scale": 3
					}
				],
				"typeProperties": {
					"schema": "dbo",
					"table": "data_source_table"
				}
			},
			"dependsOn": [
				"[concat(variables('factoryId'), '/linkedServices/AzureSqlDatabase1')]"
			]
		},
		{
			"name": "[concat(parameters('factoryName'), '/AzureSqlTable3')]",
			"type": "Microsoft.DataFactory/factories/datasets",
			"apiVersion": "2018-06-01",
			"properties": {
				"linkedServiceName": {
					"referenceName": "AzureSqlDatabase2",
					"type": "LinkedServiceReference"
				},
				"annotations": [],
				"type": "AzureSqlTable",
				"schema": [],
				"typeProperties": {
					"schema": "dbo",
					"table": "file1"
				}
			},
			"dependsOn": [
				"[concat(variables('factoryId'), '/linkedServices/AzureSqlDatabase2')]"
			]
		},
		{
			"name": "[concat(parameters('factoryName'), '/DelimitedText1')]",
			"type": "Microsoft.DataFactory/factories/datasets",
			"apiVersion": "2018-06-01",
			"properties": {
				"linkedServiceName": {
					"referenceName": "AzureBlobStorage1",
					"type": "LinkedServiceReference"
				},
				"annotations": [],
				"type": "DelimitedText",
				"typeProperties": {
					"location": {
						"type": "AzureBlobStorageLocation",
						"fileName": {
							"value": "@CONCAT('Incremental-', pipeline().TriggerTime, '.txt')",
							"type": "Expression"
						},
						"container": "incrementaldataload"
					},
					"columnDelimiter": ",",
					"escapeChar": "\\",
					"firstRowAsHeader": true,
					"quoteChar": "\""
				},
				"schema": []
			},
			"dependsOn": [
				"[concat(variables('factoryId'), '/linkedServices/AzureBlobStorage1')]"
			]
		},
		{
			"name": "[concat(parameters('factoryName'), '/DelimitedText2')]",
			"type": "Microsoft.DataFactory/factories/datasets",
			"apiVersion": "2018-06-01",
			"properties": {
				"linkedServiceName": {
					"referenceName": "AzureBlobStorage1",
					"type": "LinkedServiceReference"
				},
				"annotations": [],
				"type": "DelimitedText",
				"typeProperties": {
					"location": {
						"type": "AzureBlobStorageLocation",
						"fileName": {
							"value": "@CONCAT('Incremental-', pipeline().TriggerTime, '.txt')",
							"type": "Expression"
						},
						"folderPath": "multipletables",
						"container": "incrementaldataload"
					},
					"columnDelimiter": ",",
					"escapeChar": "\\",
					"firstRowAsHeader": true,
					"quoteChar": "\""
				},
				"schema": []
			},
			"dependsOn": [
				"[concat(variables('factoryId'), '/linkedServices/AzureBlobStorage1')]"
			]
		},
		{
			"name": "[concat(parameters('factoryName'), '/DelimitedText3')]",
			"type": "Microsoft.DataFactory/factories/datasets",
			"apiVersion": "2018-06-01",
			"properties": {
				"linkedServiceName": {
					"referenceName": "AzureBlobStorage1",
					"type": "LinkedServiceReference"
				},
				"annotations": [],
				"type": "DelimitedText",
				"typeProperties": {
					"location": {
						"type": "AzureBlobStorageLocation",
						"folderPath": "dataset",
						"container": "largedatasets"
					},
					"columnDelimiter": ",",
					"escapeChar": "\\",
					"firstRowAsHeader": true,
					"quoteChar": "\""
				},
				"schema": [
					{
						"name": "ID",
						"type": "String"
					},
					{
						"name": "Name",
						"type": "String"
					},
					{
						"name": "Age ",
						"type": "String"
					}
				]
			},
			"dependsOn": [
				"[concat(variables('factoryId'), '/linkedServices/AzureBlobStorage1')]"
			]
		},
		{
			"name": "[concat(parameters('factoryName'), '/DelimitedText4')]",
			"type": "Microsoft.DataFactory/factories/datasets",
			"apiVersion": "2018-06-01",
			"properties": {
				"linkedServiceName": {
					"referenceName": "AzureDataLakeStorage1",
					"type": "LinkedServiceReference"
				},
				"parameters": {
					"filename": {
						"type": "String"
					}
				},
				"annotations": [],
				"type": "DelimitedText",
				"typeProperties": {
					"location": {
						"type": "AzureBlobFSLocation",
						"fileName": {
							"value": "@dataset().filename",
							"type": "Expression"
						},
						"folderPath": "dataset",
						"fileSystem": "largedatasets"
					},
					"columnDelimiter": ",",
					"escapeChar": "\\",
					"firstRowAsHeader": true,
					"quoteChar": "\""
				},
				"schema": [
					{
						"name": "ID",
						"type": "String"
					},
					{
						"name": "Name",
						"type": "String"
					},
					{
						"name": "Age ",
						"type": "String"
					}
				]
			},
			"dependsOn": [
				"[concat(variables('factoryId'), '/linkedServices/AzureDataLakeStorage1')]"
			]
		},
		{
			"name": "[concat(parameters('factoryName'), '/DelimitedText5')]",
			"type": "Microsoft.DataFactory/factories/datasets",
			"apiVersion": "2018-06-01",
			"properties": {
				"linkedServiceName": {
					"referenceName": "AzureBlobStorage1",
					"type": "LinkedServiceReference"
				},
				"annotations": [],
				"type": "DelimitedText",
				"typeProperties": {
					"location": {
						"type": "AzureBlobStorageLocation",
						"fileName": "file1.csv",
						"container": "largedatasets"
					},
					"columnDelimiter": ",",
					"escapeChar": "\\",
					"firstRowAsHeader": true,
					"quoteChar": "\""
				},
				"schema": [
					{
						"name": "ID",
						"type": "String"
					},
					{
						"name": "Name",
						"type": "String"
					},
					{
						"name": "Age ",
						"type": "String"
					}
				]
			},
			"dependsOn": [
				"[concat(variables('factoryId'), '/linkedServices/AzureBlobStorage1')]"
			]
		},
		{
			"name": "[concat(parameters('factoryName'), '/DestinationDB')]",
			"type": "Microsoft.DataFactory/factories/datasets",
			"apiVersion": "2018-06-01",
			"properties": {
				"linkedServiceName": {
					"referenceName": "AzureSqlDatabase2",
					"type": "LinkedServiceReference"
				},
				"parameters": {
					"tablename": {
						"type": "String"
					}
				},
				"annotations": [],
				"type": "AzureSqlTable",
				"schema": [],
				"typeProperties": {
					"schema": "",
					"table": {
						"value": "@dataset().tablename",
						"type": "Expression"
					}
				}
			},
			"dependsOn": [
				"[concat(variables('factoryId'), '/linkedServices/AzureSqlDatabase2')]"
			]
		},
		{
			"name": "[concat(parameters('factoryName'), '/Finance')]",
			"type": "Microsoft.DataFactory/factories/datasets",
			"apiVersion": "2018-06-01",
			"properties": {
				"linkedServiceName": {
					"referenceName": "AzureSqlDatabase2",
					"type": "LinkedServiceReference"
				},
				"annotations": [],
				"type": "AzureSqlTable",
				"schema": [
					{
						"name": "Cust_ID",
						"type": "int",
						"precision": 10
					},
					{
						"name": "Customer_Name",
						"type": "varchar"
					}
				],
				"typeProperties": {
					"schema": "dbo",
					"table": "Finance"
				}
			},
			"dependsOn": [
				"[concat(variables('factoryId'), '/linkedServices/AzureSqlDatabase2')]"
			]
		},
		{
			"name": "[concat(parameters('factoryName'), '/HR')]",
			"type": "Microsoft.DataFactory/factories/datasets",
			"apiVersion": "2018-06-01",
			"properties": {
				"linkedServiceName": {
					"referenceName": "AzureSqlDatabase2",
					"type": "LinkedServiceReference"
				},
				"annotations": [],
				"type": "AzureSqlTable",
				"schema": [
					{
						"name": "Cust_ID",
						"type": "int",
						"precision": 10
					},
					{
						"name": "Customer_Name",
						"type": "varchar"
					}
				],
				"typeProperties": {
					"schema": "dbo",
					"table": "HR"
				}
			},
			"dependsOn": [
				"[concat(variables('factoryId'), '/linkedServices/AzureSqlDatabase2')]"
			]
		},
		{
			"name": "[concat(parameters('factoryName'), '/Json1')]",
			"type": "Microsoft.DataFactory/factories/datasets",
			"apiVersion": "2018-06-01",
			"properties": {
				"linkedServiceName": {
					"referenceName": "AzureDataLakeStorage1",
					"type": "LinkedServiceReference"
				},
				"annotations": [],
				"type": "Json",
				"typeProperties": {
					"location": {
						"type": "AzureBlobFSLocation",
						"fileName": "config.json",
						"folderPath": "config",
						"fileSystem": "parameterisation"
					}
				},
				"schema": {}
			},
			"dependsOn": [
				"[concat(variables('factoryId'), '/linkedServices/AzureDataLakeStorage1')]"
			]
		},
		{
			"name": "[concat(parameters('factoryName'), '/ParameterizedDB')]",
			"type": "Microsoft.DataFactory/factories/datasets",
			"apiVersion": "2018-06-01",
			"properties": {
				"linkedServiceName": {
					"referenceName": "AzureSqlDatabase3",
					"type": "LinkedServiceReference",
					"parameters": {
						"serverName": {
							"value": "@dataset().servername",
							"type": "Expression"
						},
						"databaseName": {
							"value": "@dataset().databaseName",
							"type": "Expression"
						}
					}
				},
				"parameters": {
					"tableName": {
						"type": "string"
					},
					"databaseName": {
						"type": "string"
					},
					"servername": {
						"type": "string"
					}
				},
				"annotations": [],
				"type": "AzureSqlTable",
				"schema": [],
				"typeProperties": {
					"schema": "dbo",
					"table": {
						"value": "@dataset().tableName",
						"type": "Expression"
					}
				}
			},
			"dependsOn": [
				"[concat(variables('factoryId'), '/linkedServices/AzureSqlDatabase3')]"
			]
		},
		{
			"name": "[concat(parameters('factoryName'), '/Parquet1')]",
			"type": "Microsoft.DataFactory/factories/datasets",
			"apiVersion": "2018-06-01",
			"properties": {
				"linkedServiceName": {
					"referenceName": "AzureDataLakeStorage1",
					"type": "LinkedServiceReference"
				},
				"parameters": {
					"outputfile": {
						"type": "String"
					}
				},
				"annotations": [],
				"type": "Parquet",
				"typeProperties": {
					"location": {
						"type": "AzureBlobFSLocation",
						"fileName": "output",
						"fileSystem": "customer-data"
					},
					"compressionCodec": "snappy"
				},
				"schema": []
			},
			"dependsOn": [
				"[concat(variables('factoryId'), '/linkedServices/AzureDataLakeStorage1')]"
			]
		},
		{
			"name": "[concat(parameters('factoryName'), '/SinkDataset')]",
			"type": "Microsoft.DataFactory/factories/datasets",
			"apiVersion": "2018-06-01",
			"properties": {
				"linkedServiceName": {
					"referenceName": "AzureSqlDatabase1",
					"type": "LinkedServiceReference"
				},
				"parameters": {
					"SinkTableName": {
						"type": "string"
					}
				},
				"annotations": [],
				"type": "AzureSqlTable",
				"schema": [],
				"typeProperties": {
					"schema": {
						"value": "@dataset().SinkTableName",
						"type": "Expression"
					}
				}
			},
			"dependsOn": [
				"[concat(variables('factoryId'), '/linkedServices/AzureSqlDatabase1')]"
			]
		},
		{
			"name": "[concat(parameters('factoryName'), '/SourceTables2')]",
			"type": "Microsoft.DataFactory/factories/datasets",
			"apiVersion": "2018-06-01",
			"properties": {
				"linkedServiceName": {
					"referenceName": "SqlServer1",
					"type": "LinkedServiceReference"
				},
				"annotations": [],
				"type": "SqlServerTable",
				"schema": [],
				"typeProperties": {}
			},
			"dependsOn": [
				"[concat(variables('factoryId'), '/linkedServices/SqlServer1')]"
			]
		},
		{
			"name": "[concat(parameters('factoryName'), '/configtable')]",
			"type": "Microsoft.DataFactory/factories/datasets",
			"apiVersion": "2018-06-01",
			"properties": {
				"linkedServiceName": {
					"referenceName": "AzureSqlDatabase1",
					"type": "LinkedServiceReference"
				},
				"annotations": [],
				"type": "AzureSqlTable",
				"schema": [
					{
						"name": "Id",
						"type": "int",
						"precision": 10
					},
					{
						"name": "Name",
						"type": "varchar"
					},
					{
						"name": "Type",
						"type": "varchar"
					},
					{
						"name": "Enabled",
						"type": "int",
						"precision": 10
					}
				],
				"typeProperties": {
					"schema": "dbo",
					"table": "Config"
				}
			},
			"dependsOn": [
				"[concat(variables('factoryId'), '/linkedServices/AzureSqlDatabase1')]"
			]
		},
		{
			"name": "[concat(parameters('factoryName'), '/customer1')]",
			"type": "Microsoft.DataFactory/factories/datasets",
			"apiVersion": "2018-06-01",
			"properties": {
				"linkedServiceName": {
					"referenceName": "AzureSqlDatabase1",
					"type": "LinkedServiceReference"
				},
				"annotations": [],
				"type": "AzureSqlTable",
				"schema": [
					{
						"name": "Cust_ID",
						"type": "int",
						"precision": 10
					},
					{
						"name": "Customer_Name",
						"type": "varchar"
					},
					{
						"name": "Dept_ID",
						"type": "int",
						"precision": 10
					}
				],
				"typeProperties": {
					"schema": "dbo",
					"table": "Customer1"
				}
			},
			"dependsOn": [
				"[concat(variables('factoryId'), '/linkedServices/AzureSqlDatabase1')]"
			]
		},
		{
			"name": "[concat(parameters('factoryName'), '/customerpurchases')]",
			"type": "Microsoft.DataFactory/factories/datasets",
			"apiVersion": "2018-06-01",
			"properties": {
				"linkedServiceName": {
					"referenceName": "AzureSqlDatabase1",
					"type": "LinkedServiceReference"
				},
				"annotations": [],
				"type": "AzureSqlTable",
				"schema": [
					{
						"name": "CustomerID",
						"type": "int",
						"precision": 10
					},
					{
						"name": "Month",
						"type": "varchar"
					},
					{
						"name": "PurchaseAmount",
						"type": "float",
						"precision": 15
					}
				],
				"typeProperties": {
					"schema": "dbo",
					"table": "CustomerPurchases"
				}
			},
			"dependsOn": [
				"[concat(variables('factoryId'), '/linkedServices/AzureSqlDatabase1')]"
			]
		},
		{
			"name": "[concat(parameters('factoryName'), '/customertable')]",
			"type": "Microsoft.DataFactory/factories/datasets",
			"apiVersion": "2018-06-01",
			"properties": {
				"linkedServiceName": {
					"referenceName": "AzureSqlDatabase1",
					"type": "LinkedServiceReference"
				},
				"annotations": [],
				"type": "AzureSqlTable",
				"schema": [
					{
						"name": "ID",
						"type": "int",
						"precision": 10
					},
					{
						"name": "Customer_Name",
						"type": "varchar"
					},
					{
						"name": "Salary",
						"type": "float",
						"precision": 15
					}
				],
				"typeProperties": {
					"schema": "dbo",
					"table": "Customer"
				}
			},
			"dependsOn": [
				"[concat(variables('factoryId'), '/linkedServices/AzureSqlDatabase1')]"
			]
		},
		{
			"name": "[concat(parameters('factoryName'), '/datafile')]",
			"type": "Microsoft.DataFactory/factories/datasets",
			"apiVersion": "2018-06-01",
			"properties": {
				"linkedServiceName": {
					"referenceName": "AzureDataLakeStorage1",
					"type": "LinkedServiceReference"
				},
				"parameters": {
					"sourcePath": {
						"type": "String"
					},
					"filename": {
						"type": "String"
					}
				},
				"annotations": [],
				"type": "DelimitedText",
				"typeProperties": {
					"location": {
						"type": "AzureBlobFSLocation",
						"fileName": {
							"value": "@dataset().filename",
							"type": "Expression"
						},
						"folderPath": {
							"value": "@dataset().sourcePath",
							"type": "Expression"
						},
						"fileSystem": "parameterisation"
					},
					"columnDelimiter": ",",
					"escapeChar": "\\",
					"firstRowAsHeader": true,
					"quoteChar": "\""
				},
				"schema": [
					{
						"name": "ID",
						"type": "String"
					},
					{
						"name": "Name",
						"type": "String"
					},
					{
						"name": "Status",
						"type": "String"
					},
					{
						"name": "Score ",
						"type": "String"
					}
				]
			},
			"dependsOn": [
				"[concat(variables('factoryId'), '/linkedServices/AzureDataLakeStorage1')]"
			]
		},
		{
			"name": "[concat(parameters('factoryName'), '/department')]",
			"type": "Microsoft.DataFactory/factories/datasets",
			"apiVersion": "2018-06-01",
			"properties": {
				"linkedServiceName": {
					"referenceName": "AzureSqlDatabase1",
					"type": "LinkedServiceReference"
				},
				"annotations": [],
				"type": "AzureSqlTable",
				"schema": [
					{
						"name": "Dept_ID",
						"type": "int",
						"precision": 10
					},
					{
						"name": "Dept_Name",
						"type": "varchar"
					}
				],
				"typeProperties": {
					"schema": "dbo",
					"table": "Department"
				}
			},
			"dependsOn": [
				"[concat(variables('factoryId'), '/linkedServices/AzureSqlDatabase1')]"
			]
		},
		{
			"name": "[concat(parameters('factoryName'), '/locationdetails')]",
			"type": "Microsoft.DataFactory/factories/datasets",
			"apiVersion": "2018-06-01",
			"properties": {
				"linkedServiceName": {
					"referenceName": "AzureSqlDatabase1",
					"type": "LinkedServiceReference"
				},
				"annotations": [],
				"type": "AzureSqlTable",
				"schema": [
					{
						"name": "LocationID",
						"type": "int",
						"precision": 10
					},
					{
						"name": "Region",
						"type": "varchar"
					}
				],
				"typeProperties": {
					"schema": "dbo",
					"table": "LocationDetails"
				}
			},
			"dependsOn": [
				"[concat(variables('factoryId'), '/linkedServices/AzureSqlDatabase1')]"
			]
		},
		{
			"name": "[concat(parameters('factoryName'), '/personaldetails')]",
			"type": "Microsoft.DataFactory/factories/datasets",
			"apiVersion": "2018-06-01",
			"properties": {
				"linkedServiceName": {
					"referenceName": "AzureDataLakeStorage1",
					"type": "LinkedServiceReference"
				},
				"annotations": [],
				"type": "DelimitedText",
				"typeProperties": {
					"location": {
						"type": "AzureBlobFSLocation",
						"fileName": "personal_details.csv",
						"fileSystem": "customer-data"
					},
					"columnDelimiter": ",",
					"escapeChar": "\\",
					"firstRowAsHeader": true,
					"quoteChar": "\""
				},
				"schema": [
					{
						"name": "CustomerID",
						"type": "String"
					},
					{
						"name": "FirstName",
						"type": "String"
					},
					{
						"name": "LastName",
						"type": "String"
					},
					{
						"name": "Age",
						"type": "String"
					},
					{
						"name": "IsActive",
						"type": "String"
					},
					{
						"name": "LocationID ",
						"type": "String"
					}
				]
			},
			"dependsOn": [
				"[concat(variables('factoryId'), '/linkedServices/AzureDataLakeStorage1')]"
			]
		},
		{
			"name": "[concat(parameters('factoryName'), '/processeddatatable')]",
			"type": "Microsoft.DataFactory/factories/datasets",
			"apiVersion": "2018-06-01",
			"properties": {
				"linkedServiceName": {
					"referenceName": "AzureSqlDatabase2",
					"type": "LinkedServiceReference"
				},
				"annotations": [],
				"type": "AzureSqlTable",
				"schema": [
					{
						"name": "ID",
						"type": "int",
						"precision": 10
					},
					{
						"name": "Name",
						"type": "nvarchar"
					},
					{
						"name": "Age",
						"type": "int",
						"precision": 10
					},
					{
						"name": "FileName",
						"type": "nvarchar"
					},
					{
						"name": "ProcessedDate",
						"type": "datetime",
						"precision": 23,
						"scale": 3
					}
				],
				"typeProperties": {
					"schema": "dbo",
					"table": "ProcessedData"
				}
			},
			"dependsOn": [
				"[concat(variables('factoryId'), '/linkedServices/AzureSqlDatabase2')]"
			]
		},
		{
			"name": "[concat(parameters('factoryName'), '/sourcetables')]",
			"type": "Microsoft.DataFactory/factories/datasets",
			"apiVersion": "2018-06-01",
			"properties": {
				"linkedServiceName": {
					"referenceName": "AzureSqlDatabase1",
					"type": "LinkedServiceReference"
				},
				"annotations": [],
				"type": "AzureSqlTable",
				"schema": [],
				"typeProperties": {}
			},
			"dependsOn": [
				"[concat(variables('factoryId'), '/linkedServices/AzureSqlDatabase1')]"
			]
		},
		{
			"name": "[concat(parameters('factoryName'), '/AzureBlobStorage1')]",
			"type": "Microsoft.DataFactory/factories/linkedServices",
			"apiVersion": "2018-06-01",
			"properties": {
				"annotations": [],
				"type": "AzureBlobStorage",
				"typeProperties": {
					"connectionString": "[parameters('AzureBlobStorage1_connectionString')]"
				}
			},
			"dependsOn": []
		},
		{
			"name": "[concat(parameters('factoryName'), '/AzureDataLakeStorage1')]",
			"type": "Microsoft.DataFactory/factories/linkedServices",
			"apiVersion": "2018-06-01",
			"properties": {
				"annotations": [],
				"type": "AzureBlobFS",
				"typeProperties": {
					"url": "[parameters('AzureDataLakeStorage1_properties_typeProperties_url')]",
					"accountKey": {
						"type": "SecureString",
						"value": "[parameters('AzureDataLakeStorage1_accountKey')]"
					}
				}
			},
			"dependsOn": []
		},
		{
			"name": "[concat(parameters('factoryName'), '/AzureSqlDatabase1')]",
			"type": "Microsoft.DataFactory/factories/linkedServices",
			"apiVersion": "2018-06-01",
			"properties": {
				"annotations": [],
				"type": "AzureSqlDatabase",
				"typeProperties": {
					"server": "[parameters('AzureSqlDatabase1_properties_typeProperties_server')]",
					"database": "[parameters('AzureSqlDatabase1_properties_typeProperties_database')]",
					"encrypt": "optional",
					"trustServerCertificate": true,
					"authenticationType": "SQL",
					"userName": "[parameters('AzureSqlDatabase1_properties_typeProperties_userName')]",
					"password": {
						"type": "SecureString",
						"value": "[parameters('AzureSqlDatabase1_password')]"
					}
				}
			},
			"dependsOn": []
		},
		{
			"name": "[concat(parameters('factoryName'), '/AzureSqlDatabase2')]",
			"type": "Microsoft.DataFactory/factories/linkedServices",
			"apiVersion": "2018-06-01",
			"properties": {
				"annotations": [],
				"type": "AzureSqlDatabase",
				"typeProperties": {
					"server": "[parameters('AzureSqlDatabase2_properties_typeProperties_server')]",
					"database": "[parameters('AzureSqlDatabase2_properties_typeProperties_database')]",
					"encrypt": "optional",
					"trustServerCertificate": true,
					"authenticationType": "SQL",
					"userName": "[parameters('AzureSqlDatabase2_properties_typeProperties_userName')]",
					"password": {
						"type": "SecureString",
						"value": "[parameters('AzureSqlDatabase2_password')]"
					}
				}
			},
			"dependsOn": []
		},
		{
			"name": "[concat(parameters('factoryName'), '/AzureSqlDatabase3')]",
			"type": "Microsoft.DataFactory/factories/linkedServices",
			"apiVersion": "2018-06-01",
			"properties": {
				"parameters": {
					"serverName": {
						"type": "string"
					},
					"databaseName": {
						"type": "string"
					}
				},
				"annotations": [],
				"type": "AzureSqlDatabase",
				"typeProperties": {
					"server": "[parameters('AzureSqlDatabase3_properties_typeProperties_server')]",
					"database": "[parameters('AzureSqlDatabase3_properties_typeProperties_database')]",
					"encrypt": "optional",
					"trustServerCertificate": true,
					"authenticationType": "SQL",
					"userName": "[parameters('AzureSqlDatabase3_properties_typeProperties_userName')]",
					"password": {
						"type": "SecureString",
						"value": "[parameters('AzureSqlDatabase3_password')]"
					}
				}
			},
			"dependsOn": []
		},
		{
			"name": "[concat(parameters('factoryName'), '/FileServer1')]",
			"type": "Microsoft.DataFactory/factories/linkedServices",
			"apiVersion": "2018-06-01",
			"properties": {
				"annotations": [],
				"type": "FileServer",
				"typeProperties": {
					"host": "[parameters('FileServer1_properties_typeProperties_host')]",
					"userId": "[parameters('FileServer1_properties_typeProperties_userId')]",
					"password": {
						"type": "SecureString",
						"value": "[parameters('FileServer1_password')]"
					}
				},
				"connectVia": {
					"referenceName": "SelfHostedIR",
					"type": "IntegrationRuntimeReference"
				}
			},
			"dependsOn": [
				"[concat(variables('factoryId'), '/integrationRuntimes/SelfHostedIR')]"
			]
		},
		{
			"name": "[concat(parameters('factoryName'), '/SqlServer1')]",
			"type": "Microsoft.DataFactory/factories/linkedServices",
			"apiVersion": "2018-06-01",
			"properties": {
				"annotations": [],
				"type": "SqlServer",
				"typeProperties": {
					"server": "[parameters('SqlServer1_properties_typeProperties_server')]",
					"database": "[parameters('SqlServer1_properties_typeProperties_database')]",
					"encrypt": "optional",
					"trustServerCertificate": true,
					"authenticationType": "SQL",
					"userName": "[parameters('SqlServer1_properties_typeProperties_userName')]",
					"password": {
						"type": "SecureString",
						"value": "[parameters('SqlServer1_password')]"
					}
				},
				"connectVia": {
					"referenceName": "SelfHostedIR",
					"type": "IntegrationRuntimeReference"
				}
			},
			"dependsOn": [
				"[concat(variables('factoryId'), '/integrationRuntimes/SelfHostedIR')]"
			]
		},
		{
			"name": "[concat(parameters('factoryName'), '/SelfHostedIR')]",
			"type": "Microsoft.DataFactory/factories/integrationRuntimes",
			"apiVersion": "2018-06-01",
			"properties": {
				"type": "SelfHosted",
				"typeProperties": {}
			},
			"dependsOn": []
		},
		{
			"name": "[concat(parameters('factoryName'), '/dataflow1')]",
			"type": "Microsoft.DataFactory/factories/dataflows",
			"apiVersion": "2018-06-01",
			"properties": {
				"type": "MappingDataFlow",
				"typeProperties": {
					"sources": [
						{
							"dataset": {
								"referenceName": "personaldetails",
								"type": "DatasetReference"
							},
							"name": "Personaldetails"
						},
						{
							"dataset": {
								"referenceName": "locationdetails",
								"type": "DatasetReference"
							},
							"name": "locationdetails"
						},
						{
							"dataset": {
								"referenceName": "customerpurchases",
								"type": "DatasetReference"
							},
							"name": "customerpurchases"
						}
					],
					"sinks": [
						{
							"dataset": {
								"referenceName": "Parquet1",
								"type": "DatasetReference"
							},
							"name": "sink1"
						}
					],
					"transformations": [
						{
							"name": "derivedColumn1"
						},
						{
							"name": "filter1"
						},
						{
							"name": "lookup1"
						},
						{
							"name": "aggregate1"
						},
						{
							"name": "join1"
						},
						{
							"name": "sort1"
						},
						{
							"name": "surrogateKey"
						},
						{
							"name": "select1"
						},
						{
							"name": "CustomerSegment"
						}
					],
					"scriptLines": [
						"source(output(",
						"          CustomerID as integer,",
						"          FirstName as string,",
						"          LastName as string,",
						"          Age as integer,",
						"          IsActive as boolean,",
						"          {LocationID } as integer",
						"     ),",
						"     allowSchemaDrift: true,",
						"     validateSchema: false,",
						"     ignoreNoFilesFound: false) ~> Personaldetails",
						"source(output(",
						"          LocationID as integer,",
						"          Region as string",
						"     ),",
						"     allowSchemaDrift: true,",
						"     validateSchema: false,",
						"     isolationLevel: 'READ_UNCOMMITTED',",
						"     format: 'table') ~> locationdetails",
						"source(output(",
						"          CustomerID as integer,",
						"          Month as string,",
						"          PurchaseAmount as double",
						"     ),",
						"     allowSchemaDrift: true,",
						"     validateSchema: false,",
						"     isolationLevel: 'READ_UNCOMMITTED',",
						"     format: 'table') ~> customerpurchases",
						"Personaldetails derive(Fullname = concat(FirstName, ' ', LastName)) ~> derivedColumn1",
						"derivedColumn1 filter(equals(IsActive,true()) && greaterOrEqual(Age,18)) ~> filter1",
						"filter1, locationdetails lookup({LocationID } == LocationID,",
						"     multiple: false,",
						"     pickup: 'any',",
						"     broadcast: 'auto')~> lookup1",
						"customerpurchases aggregate(groupBy(CustomerID),",
						"     TotalSpend = sum(PurchaseAmount)) ~> aggregate1",
						"lookup1, CustomerSegment join(Personaldetails@CustomerID == aggregate1@CustomerID,",
						"     joinType:'inner',",
						"     matchType:'exact',",
						"     ignoreSpaces: false,",
						"     broadcast: 'auto')~> join1",
						"join1 sort(asc(Fullname, true)) ~> sort1",
						"select1 keyGenerate(output(CustomerKey as long),",
						"     startAt: 1L,",
						"     stepValue: 1L) ~> surrogateKey",
						"sort1 select(mapColumn(",
						"          CustomerID = Personaldetails@CustomerID,",
						"          FullName = Fullname,",
						"          Age,",
						"          Region,",
						"          TotalSpend,",
						"          CustomerSegment",
						"     ),",
						"     skipDuplicateMapInputs: true,",
						"     skipDuplicateMapOutputs: true) ~> select1",
						"aggregate1 derive(CustomerSegment = iif(TotalSpend > 5000, 'High Spender', iif(TotalSpend >= 1000, 'Medium Spender', 'Low Spender'))) ~> CustomerSegment",
						"surrogateKey sink(allowSchemaDrift: true,",
						"     validateSchema: false,",
						"     format: 'parquet',",
						"     umask: 0022,",
						"     preCommands: [],",
						"     postCommands: [],",
						"     skipDuplicateMapInputs: true,",
						"     skipDuplicateMapOutputs: true) ~> sink1"
					]
				}
			},
			"dependsOn": [
				"[concat(variables('factoryId'), '/datasets/personaldetails')]",
				"[concat(variables('factoryId'), '/datasets/locationdetails')]",
				"[concat(variables('factoryId'), '/datasets/customerpurchases')]",
				"[concat(variables('factoryId'), '/datasets/Parquet1')]"
			]
		},
		{
			"name": "[concat(parameters('factoryName'), '/dataflow2')]",
			"type": "Microsoft.DataFactory/factories/dataflows",
			"apiVersion": "2018-06-01",
			"properties": {
				"type": "MappingDataFlow",
				"typeProperties": {
					"sources": [
						{
							"dataset": {
								"referenceName": "customer1",
								"type": "DatasetReference"
							},
							"name": "source1"
						},
						{
							"dataset": {
								"referenceName": "department",
								"type": "DatasetReference"
							},
							"name": "source2"
						}
					],
					"sinks": [
						{
							"dataset": {
								"referenceName": "HR",
								"type": "DatasetReference"
							},
							"name": "sink1"
						},
						{
							"dataset": {
								"referenceName": "Finance",
								"type": "DatasetReference"
							},
							"name": "sink2"
						}
					],
					"transformations": [
						{
							"name": "join1"
						},
						{
							"name": "split1"
						}
					],
					"scriptLines": [
						"source(output(",
						"          Cust_ID as integer,",
						"          Customer_Name as string,",
						"          Dept_ID as integer",
						"     ),",
						"     allowSchemaDrift: true,",
						"     validateSchema: false,",
						"     isolationLevel: 'READ_UNCOMMITTED',",
						"     format: 'table') ~> source1",
						"source(output(",
						"          Dept_ID as integer,",
						"          Dept_Name as string",
						"     ),",
						"     allowSchemaDrift: true,",
						"     validateSchema: false,",
						"     isolationLevel: 'READ_UNCOMMITTED',",
						"     format: 'table') ~> source2",
						"source1, source2 join(source1@Dept_ID == source2@Dept_ID,",
						"     joinType:'inner',",
						"     matchType:'exact',",
						"     ignoreSpaces: false,",
						"     broadcast: 'auto')~> join1",
						"join1 split(Dept_Name == 'HR',",
						"     Dept_Name == 'Finance',",
						"     disjoint: false) ~> split1@(HR, Finance)",
						"split1@HR sink(allowSchemaDrift: true,",
						"     validateSchema: false,",
						"     input(",
						"          Cust_ID as integer,",
						"          Customer_Name as string",
						"     ),",
						"     deletable:false,",
						"     insertable:true,",
						"     updateable:false,",
						"     upsertable:false,",
						"     format: 'table',",
						"     skipDuplicateMapInputs: true,",
						"     skipDuplicateMapOutputs: true,",
						"     errorHandlingOption: 'stopOnFirstError') ~> sink1",
						"split1@Finance sink(allowSchemaDrift: true,",
						"     validateSchema: false,",
						"     input(",
						"          Cust_ID as integer,",
						"          Customer_Name as string",
						"     ),",
						"     deletable:false,",
						"     insertable:true,",
						"     updateable:false,",
						"     upsertable:false,",
						"     format: 'table',",
						"     skipDuplicateMapInputs: true,",
						"     skipDuplicateMapOutputs: true,",
						"     errorHandlingOption: 'stopOnFirstError') ~> sink2"
					]
				}
			},
			"dependsOn": [
				"[concat(variables('factoryId'), '/datasets/customer1')]",
				"[concat(variables('factoryId'), '/datasets/department')]",
				"[concat(variables('factoryId'), '/datasets/HR')]",
				"[concat(variables('factoryId'), '/datasets/Finance')]"
			]
		},
		{
			"name": "[concat(parameters('factoryName'), '/dataflow3')]",
			"type": "Microsoft.DataFactory/factories/dataflows",
			"apiVersion": "2018-06-01",
			"properties": {
				"type": "MappingDataFlow",
				"typeProperties": {
					"sources": [
						{
							"linkedService": {
								"referenceName": "AzureDataLakeStorage1",
								"type": "LinkedServiceReference"
							},
							"name": "source1"
						}
					],
					"sinks": [
						{
							"dataset": {
								"referenceName": "ParameterizedDB",
								"type": "DatasetReference"
							},
							"name": "sink1"
						}
					],
					"transformations": [
						{
							"name": "filter1"
						},
						{
							"name": "derivedColumn1"
						},
						{
							"name": "alterRow1"
						}
					],
					"scriptLines": [
						"parameters{",
						"     adlsPath as string,",
						"     fileName as string",
						"}",
						"source(output(",
						"          ID as short,",
						"          Name as string,",
						"          Status as string,",
						"          {Score } as short",
						"     ),",
						"     useSchema: false,",
						"     allowSchemaDrift: true,",
						"     validateSchema: false,",
						"     ignoreNoFilesFound: false,",
						"     format: 'delimited',",
						"     fileSystem: 'parameterisation',",
						"     folderPath: ($adlsPath),",
						"     fileName: ($fileName),",
						"     columnDelimiter: ',',",
						"     escapeChar: '\\\\',",
						"     quoteChar: '\\\"',",
						"     columnNamesAsHeader: true) ~> source1",
						"derivedColumn1 filter(equals(Status,\"Active\")) ~> filter1",
						"source1 derive(LoadDate = currentDate()) ~> derivedColumn1",
						"filter1 alterRow(updateIf(true())) ~> alterRow1",
						"alterRow1 sink(allowSchemaDrift: true,",
						"     validateSchema: false,",
						"     deletable:false,",
						"     insertable:true,",
						"     updateable:false,",
						"     upsertable:true,",
						"     keys:['ID'],",
						"     format: 'table',",
						"     skipDuplicateMapInputs: true,",
						"     skipDuplicateMapOutputs: true,",
						"     errorHandlingOption: 'stopOnFirstError') ~> sink1"
					]
				}
			},
			"dependsOn": [
				"[concat(variables('factoryId'), '/linkedServices/AzureDataLakeStorage1')]",
				"[concat(variables('factoryId'), '/datasets/ParameterizedDB')]"
			]
		}
	]
}